{
  "intents": [
    {
      "tag": "greeting",
      "patterns": [
        "xin chรo",
        "chรo bแบกn",
        "hello",
        "hi",
        "chรo buแปi sรกng",
        "chรo buแปi chiแปu",
        "chรo buแปi tแปi",
        "chรo shop",
        "alo",
        "cรณ ai แป ฤรณ khรดng",
        "รช",
        "nรy",
        "hello bแบกn",
        "xin chรo shop"
      ],
      "responses": [
        "Xin chรo! Tรดi cรณ thแป giรบp gรฌ cho bแบกn hรดm nay แบก?",
        "Chรo bแบกn! Mรฌnh lร trแปฃ lรฝ ฤแบทt ฤแป ฤn, bแบกn cแบงn tฦฐ vแบฅn mรณn gรฌ แบก?",
        "Xin chรo! Hรดm nay bแบกn muแปn thฦฐแปng thแปฉc mรณn gรฌ แบก?",
        "Chรo mแปซng bแบกn ฤแบฟn vแปi cแปญa hรng cแปงa chรบng tรดi! Bแบกn muแปn ฤแบทt mรณn gรฌ แบก?",
        "Xin chรo! Mรฌnh cรณ thแป giรบp gรฌ cho bแปฏa ฤn cแปงa bแบกn hรดm nay?"
      ]
    },
    {
      "tag": "order_food",
      "patterns": [
        "tรดi muแปn ฤแบทt mรณn",
        "cho tรดi ฤแบทt ฤแป ฤn",
        "mรฌnh muแปn gแปi mรณn",
        "ฤแบทt ฤแป ฤn",
        "gแปi mรณn",
        "tรดi muแปn ฤn",
        "cho tรดi mรณn",
        "ฤแบทt giรบp tรดi",
        "tรดi cแบงn ฤแบทt mรณn",
        "mรฌnh muแปn ฤแบทt ฤแป ฤn",
        "ฤแบทt mรณn giรบp mรฌnh",
        "tรดi ฤแบทt mรณn",
        "cho tรดi gแปi mรณn",
        "muแปn ฤแบทt mรณn ฤn",
        "tรดi cแบงn gแปi ฤแป ฤn",
        "ฤแบทt giรบp tรดi mรณn"
      ],
      "responses": [
        "Vรขng แบก! Bแบกn muแปn ฤแบทt mรณn gรฌ แบก?",
        "Mแปi bแบกn chแปn mรณn bแบกn muแปn ฤแบทt. Chรบng tรดi cรณ nhiแปu mรณn ngon ฤang chแป bแบกn khรกm phรก แบก!",
        "Bแบกn thรญch mรณn gรฌ? Tรดi sแบฝ giรบp bแบกn ฤแบทt ngay แบก.",
        "Vรขng, mแปi bแบกn chแปn mรณn แบก. Bแบกn cรณ thแป kแป tรชn mรณn hoแบทc xem thแปฑc ฤฦกn cแปงa chรบng tรดi.",
        "ฤฦฐแปฃc rแปi แบก! Bแบกn muแปn ฤn gรฌ hรดm nay?"
      ]
    },
    {
      "tag": "food_item",
      "patterns": [
        "phแป bรฒ",
        "bรบn bรฒ",
        "cฦกm gร",
        "bรกnh mรฌ",
        "bรบn ฤแบญu mแบฏm tรดm",
        "phแป gร",
        "bรกnh xรจo",
        "hแปง tiแบฟu",
        "bรบn riรชu",
        "bรกnh cuแปn",
        "xรดi",
        "chรกo lรฒng",
        "bรบn chแบฃ",
        "cฦกm tแบฅm",
        "bรกnh trรกng trแปn",
        "cฦกm sฦฐแปn",
        "bรบn thแปt nฦฐแปng",
        "phแป cuแปn",
        "bรกnh canh",
        "bรบn mแปc",
        "bรกnh mรฌ pate",
        "bรบn ฤแบญu",
        "bรกnh ฤa cua",
        "bรบn แปc",
        "bรกnh khแปt",
        "bรกnh bรจo",
        "bรกnh nแบญm",
        "bรกnh bแปt lแปc",
        "bรบn mแบฏm",
        "bรกnh ฤรบc",
        "bรกnh cuแปn thแปt nฦฐแปng",
        "bรกnh xรจo tรดm nhแบฃy",
        "bรบn bรฒ huแบฟ",
        "bรกnh mรฌ xรญu mแบกi",
        "bรกnh mรฌ chแบฃo",
        "bรกnh mรฌ trแปฉng"
      ],
      "responses": [
        "Bแบกn muแปn ฤแบทt mรณn %s ฤรบng khรดng แบก?",
        "%s lร lแปฑa chแปn tuyแปt vแปi. Bแบกn muแปn ฤแบทt mแบฅy phแบงn แบก?",
        "%s ฤang cรณ sแบตn. Bแบกn muแปn ฤแบทt bao nhiรชu phแบงn แบก?",
        "Mรณn %s cแปงa chรบng tรดi rแบฅt ฤฦฐแปฃc ฦฐa chuแปng. Bแบกn muแปn ฤแบทt mแบฅy phแบงn แบก?",
        "Vรขng, %s ฤang cรณ sแบตn. Bแบกn muแปn ฤแบทt mแบฅy phแบงn แบก?"
      ]
    },
    {
      "tag": "quantity",
      "patterns": [
        "1 phแบงn",
        "mแปt phแบงn",
        "2 phแบงn",
        "hai phแบงn",
        "3 phแบงn",
        "ba phแบงn",
        "4 phแบงn",
        "bแปn phแบงn",
        "5 phแบงn",
        "nฤm phแบงn",
        "6 phแบงn",
        "sรกu phแบงn",
        "7 phแบงn",
        "bแบฃy phแบงn",
        "8 phแบงn",
        "tรกm phแบงn",
        "9 phแบงn",
        "chรญn phแบงn",
        "10 phแบงn",
        "mฦฐแปi phแบงn",
        "mแปt suแบฅt",
        "hai suแบฅt",
        "ba suแบฅt",
        "bแปn suแบฅt",
        "nฤm suแบฅt",
        "mแปt ฤฤฉa",
        "hai ฤฤฉa",
        "mแปt tรด",
        "hai tรด",
        "mแปt dฤฉa",
        "hai dฤฉa"
      ],
      "responses": [
        "ฤรฃ ghi nhแบญn %s. Bแบกn cรณ muแปn thรชm mรณn gรฌ nแปฏa khรดng แบก?",
        "ฤรฃ thรชm %s vรo ฤฦกn hรng. Bแบกn muแปn gแปi thรชm mรณn gรฌ nแปฏa khรดng?",
        "%s ฤรฃ ฤฦฐแปฃc thรชm vรo giแป. Bแบกn cรฒn muแปn ฤแบทt thรชm gรฌ khรดng?",
        "Vรขng, %s ฤรฃ ฤฦฐแปฃc thรชm vรo ฤฦกn hรng. Bแบกn cรณ muแปn gแปi thรชm mรณn gรฌ nแปฏa khรดng แบก?",
        "ฤรฃ cแบญp nhแบญt %s. Bแบกn cรฒn muแปn ฤแบทt thรชm mรณn nรo nแปฏa khรดng แบก?"
      ]
    },
    {
      "tag": "menu",
      "patterns": [
        "cho xem menu",
        "thแปฑc ฤฦกn cรณ gรฌ",
        "cรณ mรณn gรฌ ngon",
        "hรดm nay cรณ gรฌ ngon",
        "cho xem thแปฑc ฤฦกn",
        "cรณ mรณn gรฌ ฤแบทc biแปt",
        "menu hรดm nay",
        "cรณ nhแปฏng mรณn gรฌ",
        "cho mรฌnh xem menu",
        "cรณ mรณn nรo ngon",
        "giแปi thiแปu mรณn ฤn",
        "cรณ mรณn gรฌ mแปi",
        "mรณn ฤแบทc sแบฃn lร gรฌ",
        "mรณn bรกn chแบกy",
        "mรณn nรo ngon nhแบฅt",
        "cรณ mรณn chay khรดng",
        "thแปฑc ฤฦกn hรดm nay"
      ],
      "responses": [
        "ฤรขy lร thแปฑc ฤฦกn cแปงa chรบng tรดi แบก:\n- Phแป bรฒ: 40,000ฤ\n- Bรบn bรฒ: 35,000ฤ\n- Cฦกm gร: 35,000ฤ\n- Bรกnh mรฌ: 20,000ฤ\n- Bรบn ฤแบญu mแบฏm tรดm: 45,000ฤ\n- Phแป gร: 35,000ฤ\n- Bรกnh xรจo: 40,000ฤ\n- Hแปง tiแบฟu: 35,000ฤ\n- Bรบn riรชu: 30,000ฤ\n- Bรกnh cuแปn: 35,000ฤ\n- Xรดi: 25,000ฤ\n- Chรกo lรฒng: 35,000ฤ\n- Bรบn chแบฃ: 40,000ฤ\n- Cฦกm tแบฅm: 40,000ฤ\n- Bรกnh trรกng trแปn: 25,000ฤ\n\nBแบกn muแปn ฤแบทt mรณn nรo แบก?",
        "Mแปi bแบกn xem thแปฑc ฤฦกn cแปงa chรบng tรดi แบก:\n\nMรN CHรNH:\n- Phแป bรฒ: 40,000ฤ\n- Bรบn bรฒ: 35,000ฤ\n- Cฦกm gร: 35,000ฤ\n- Bรบn ฤแบญu mแบฏm tรดm: 45,000ฤ\n- Phแป gร: 35,000ฤ\n- Bรกnh xรจo: 40,000ฤ\n- Hแปง tiแบฟu: 35,000ฤ\n- Bรบn riรชu: 30,000ฤ\n\nMรN PHแปค/ฤN VแบถT:\n- Bรกnh mรฌ: 20,000ฤ\n- Bรกnh cuแปn: 35,000ฤ\n- Xรดi: 25,000ฤ\n- Bรกnh trรกng trแปn: 25,000ฤ\n- Chรกo lรฒng: 35,000ฤ\n- Bรบn chแบฃ: 40,000ฤ\n- Cฦกm tแบฅm: 40,000ฤ\n\nBแบกn thรญch mรณn nรo แบก?",
        "Chรบng tรดi cรณ cรกc mรณn sau แบก:\n\nฤแบถC SแบขN:\n- Bรบn ฤแบญu mแบฏm tรดm: 45,000ฤ\n- Phแป bรฒ: 40,000ฤ\n- Bรกnh xรจo: 40,000ฤ\n- Bรบn chแบฃ: 40,000ฤ\n\nMรN PHแป BIแบพN:\n- Cฦกm gร: 35,000ฤ\n- Phแป gร: 35,000ฤ\n- Hแปง tiแบฟu: 35,000ฤ\n- Bรบn riรชu: 30,000ฤ\n- Bรกnh cuแปn: 35,000ฤ\n\nฤแป UแปNG:\n- Nฦฐแปc ngแปt: 15,000ฤ\n- Trร ฤรก: 5,000ฤ\n- Nฦฐแปc suแปi: 10,000ฤ\n\nBแบกn muแปn ฤแบทt mรณn gรฌ แบก?"
      ]
    },
    {
      "tag": "thanks",
      "patterns": [
        "cแบฃm ฦกn",
        "cแบฃm ฦกn bแบกn",
        "cรกm ฦกn",
        "cรกm ฦกn nhiแปu",
        "tแปt lแบฏm",
        "tuyแปt vแปi",
        "cแบฃm ฦกn nhรฉ",
        "cแบฃm ฦกn shop",
        "cแบฃm ฦกn nha",
        "cแบฃm ฦกn rแบฅt nhiแปu",
        "cรกm ฦกn shop",
        "cรกm ฦกn nha",
        "cรกm ฦกn rแบฅt nhiแปu",
        "ok cแบฃm ฦกn",
        "ฤฦฐแปฃc rแปi cแบฃm ฦกn",
        "tuyแปt vแปi cแบฃm ฦกn",
        "tแปt quรก cแบฃm ฦกn",
        "cแบฃm ฦกn ad"
      ],
      "responses": [
        "Khรดng cรณ gรฌ แบก! Rแบฅt vui ฤฦฐแปฃc phแปฅc vแปฅ bแบกn.",
        "Cแบฃm ฦกn bแบกn ฤรฃ sแปญ dแปฅng dแปch vแปฅ cแปงa chรบng tรดi! Nแบฟu cแบงn thรชm gรฌ bแบกn cแปฉ nรณi nhรฉ!",
        "Rแบฅt hรขn hแบกnh ฤฦฐแปฃc phแปฅc vแปฅ bแบกn แบก! Chรบc bแบกn ngon miแปng!",
        "Khรดng cรณ chi แบก! Nแบฟu cแบงn thรชm gรฌ bแบกn cแปฉ gแปi mรฌnh nhรฉ!",
        "Cแบฃm ฦกn bแบกn ฤรฃ tin tฦฐแปng แบก! Hแบนn gแบทp lแบกi bแบกn trong nhแปฏng lแบงn sau!"
      ]
    },
    {
      "tag": "goodbye",
      "patterns": [
        "tแบกm biแปt",
        "hแบนn gแบทp lแบกi",
        "bye",
        "tแบกm biแปt nhรฉ",
        "hแบนn lแบงn sau",
        "thรดi tแบกm biแปt",
        "thรดi ฤi ฤรขy",
        "thรดi ฤแป lรบc khรกc",
        "thรดi tรดi ฤi ฤรขy",
        "bye bye",
        "bรกi bai",
        "tแบกm biแปt nha",
        "hแบนn gแบทp lแบกi sau",
        "thรดi tรดi off ฤรขy",
        "thรดi tรดi ฤi ngแปง ฤรขy",
        "hแบนn gแบทp lแบกi bแบกn sau"
      ],
      "responses": [
        "Tแบกm biแปt bแบกn! Hแบนn gแบทp lแบกi lแบงn sau แบก!",
        "Cแบฃm ฦกn bแบกn ฤรฃ ghรฉ thฤm. Hแบนn gแบทp lแบกi bแบกn trong nhแปฏng lแบงn sau nhรฉ!",
        "Chรบc bแบกn mแปt ngรy tแปt lรnh! Hแบนn gแบทp lแบกi แบก!",
        "Tแบกm biแปt bแบกn! Nแบฟu cแบงn gรฌ cแปฉ quay lแบกi nhรฉ!",
        "Hแบนn gแบทp lแบกi bแบกn trong nhแปฏng lแบงn ฤแบทt hรng tiแบฟp theo แบก!"
      ]
    },
    {
      "tag": "delivery",
      "patterns": [
        "cรณ ship khรดng",
        "giao hรng thแบฟ nรo",
        "phรญ ship bao nhiรชu",
        "cรณ giao hรng tแบญn nฦกi khรดng",
        "ship cod ฤฦฐแปฃc khรดng",
        "cรณ giao hรng khรดng",
        "giao hรng mแบฅt bao lรขu",
        "thแปi gian giao hรng",
        "ship tแบญn nฦกi khรดng",
        "giao hรng nhanh khรดng",
        "cรณ giao hรng ngoแบกi thรnh khรดng",
        "ship nhanh khรดng",
        "cรณ giao hรng giแป hรnh chรญnh khรดng",
        "cรณ ship tแปi khรดng",
        "giao hรng nhanh nhแบฅt lรบc mแบฅy giแป",
        "cรณ giao hรng ฤรชm khรดng"
      ],
      "responses": [
        "Chรบng tรดi cรณ dแปch vแปฅ giao hรng tแบญn nฦกi vแปi phรญ ship 15,000ฤ cho ฤฦกn dฦฐแปi 50,000ฤ. ฤฦกn tแปซ 50,000ฤ trแป lรชn ฤฦฐแปฃc miแปn phรญ ship แบก. Thแปi gian giao hรng tแปซ 20-30 phรบt trong bรกn kรญnh 5km.",
        "Phรญ ship lร 15,000ฤ cho ฤฦกn dฦฐแปi 50,000ฤ. ฤฦกn tแปซ 50,000ฤ trแป lรชn ฤฦฐแปฃc miแปn phรญ ship. Chรบng tรดi giao hรng tแปซ 6h sรกng ฤแบฟn 21h tแปi hรng ngรy แบก.",
        "Chรบng tรดi hแป trแปฃ giao hรng tแบญn nฦกi. Phรญ ship 15,000ฤ cho ฤฦกn dฦฐแปi 50,000ฤ, miแปn phรญ ship cho ฤฦกn tแปซ 50,000ฤ trแป lรชn. Thแปi gian giao hรng tแปซ 20-45 phรบt tรนy ฤแปa chแป แบก.",
        "Vรขng, chรบng tรดi cรณ giao hรng tแบญn nฦกi แบก. Phรญ ship 15,000ฤ cho ฤฦกn dฦฐแปi 50,000ฤ, ฤฦกn tแปซ 50,000ฤ trแป lรชn ฤฦฐแปฃc miแปn phรญ ship. Thแปi gian giao hรng tแปซ 20-30 phรบt trong nแปi thรnh แบก.",
        "Chรบng tรดi giao hรng tแบญn nฦกi tแปซ 6h sรกng ฤแบฟn 21h tแปi hรng ngรy. Phรญ ship 15,000ฤ cho ฤฦกn dฦฐแปi 50,000ฤ, miแปn phรญ ship cho ฤฦกn tแปซ 50,000ฤ trแป lรชn แบก."
      ]
    },
    {
      "tag": "payment",
      "patterns": [
        "thanh toรกn thแบฟ nรo",
        "cรณ nhแบญn thแบป khรดng",
        "thanh toรกn online ฤฦฐแปฃc khรดng",
        "cรณ nhแบญn momo khรดng",
        "trแบฃ tiแปn mแบทt ฤฦฐแปฃc khรดng",
        "cรณ chuyแปn khoแบฃn ฤฦฐแปฃc khรดng",
        "thanh toรกn bแบฑng gรฌ",
        "cรณ nhแบญn zalo pay khรดng",
        "cรณ nhแบญn vรญ ฤiแปn tแปญ khรดng",
        "thanh toรกn khi nhแบญn hรng ฤฦฐแปฃc khรดng",
        "cรณ nhแบญn thแบป visa khรดng",
        "cรณ nhแบญn thแบป mastercard khรดng",
        "cรณ nhแบญn thแบป quแปc tแบฟ khรดng",
        "cรณ nhแบญn tiแปn mแบทt khรดng",
        "cรณ nhแบญn tiแปn mแบทt khi giao hรng khรดng",
        "cรณ nhแบญn thแบป nแปi ฤแปa khรดng"
      ],
      "responses": [
        "Chรบng tรดi chแบฅp nhแบญn nhiแปu hรฌnh thแปฉc thanh toรกn แบก:\n- Tiแปn mแบทt khi nhแบญn hรng (COD)\n- Chuyแปn khoแบฃn ngรขn hรng\n- Vรญ ฤiแปn tแปญ: Momo, ZaloPay, VNPay\n- Thแบป tรญn dแปฅng/quแปc tแบฟ: Visa, Mastercard, JCB\n- Thแบป ATM nแปi ฤแปa",
        "Bแบกn cรณ thแป thanh toรกn bแบฑng nhiแปu cรกch tiแปn lแปฃi แบก:\n1. Tiแปn mแบทt khi nhแบญn hรng\n2. Chuyแปn khoแบฃn ngรขn hรng\n3. Quรฉt mรฃ QR qua Momo, ZaloPay\n4. Thแบป tรญn dแปฅng/quแปc tแบฟ\nBแบกn muแปn thanh toรกn bแบฑng hรฌnh thแปฉc nรo แบก?",
        "Chรบng tรดi hแป trแปฃ ฤa dแบกng hรฌnh thแปฉc thanh toรกn ฤแป phแปฅc vแปฅ quรฝ khรกch tแปt nhแบฅt แบก:\n\nโข Tiแปn mแบทt khi nhแบญn hรng (COD)\nโข Chuyแปn khoแบฃn ngรขn hรng\nโข Vรญ ฤiแปn tแปญ: Momo, ZaloPay, VNPay\nโข Thแบป tรญn dแปฅng/quแปc tแบฟ: Visa, Mastercard, JCB\nโข Thแบป ATM nแปi ฤแปa\n\nBแบกn muแปn thanh toรกn bแบฑng hรฌnh thแปฉc nรo แบก?"
      ]
    },
    {
      "tag": "hours",
      "patterns": [
        "mแบฅy giแป mแป cแปญa",
        "thแปi gian mแป cแปญa",
        "cแปญa hรng mแป ฤแบฟn mแบฅy giแป",
        "cรณ mแป cแปญa khรดng",
        "hรดm nay cรณ mแป khรดng",
        "mแป cแปญa lรบc mแบฅy giแป",
        "ฤรณng cแปญa lรบc mแบฅy giแป",
        "thแปฉ 7 cรณ mแป khรดng",
        "chแปง nhแบญt cรณ mแป khรดng",
        "tแบฟt cรณ mแป khรดng",
        "lแป cรณ mแป cแปญa khรดng",
        "cรณ phแปฅc vแปฅ sรกng sแปm khรดng",
        "cรณ phแปฅc vแปฅ ฤรชm khuya khรดng",
        "cรณ mแป cแปญa thแปฉ 2 khรดng",
        "cรณ mแป cแปญa cuแปi tuแบงn khรดng",
        "cรณ mแป cแปญa ngรy lแป khรดng"
      ],
      "responses": [
        "Cแปญa hรng chรบng tรดi mแป cแปญa tแบฅt cแบฃ cรกc ngรy trong tuแบงn tแปซ 6h00 sรกng ฤแบฟn 22h00 tแปi แบก. Riรชng thแปฉ 7 vร chแปง nhแบญt mแป ฤแบฟn 23h00 tแปi ฤแป phแปฅc vแปฅ quรฝ khรกch.",
        "Chรบng tรดi phแปฅc vแปฅ tแปซ 6:00 sรกng ฤแบฟn 22:00 tแปi hรng ngรy. Thแปฉ 7 vร chแปง nhแบญt mแป cแปญa ฤแบฟn 23h00 tแปi แบก. Cรกc ngรy lแป vแบซn mแป cแปญa bรฌnh thฦฐแปng.",
        "Giแป mแป cแปญa cแปงa chรบng tรดi แบก:\nโข Thแปฉ 2 - Thแปฉ 6: 6h00 - 22h00\nโข Thแปฉ 7 - Chแปง nhแบญt: 6h00 - 23h00\n\nCรกc ngรy lแป vแบซn mแป cแปญa bรฌnh thฦฐแปng. Nแบฟu cรณ thay ฤแปi, chรบng tรดi sแบฝ thรดng bรกo trฦฐแปc แบก.",
        "Chรบng tรดi mแป cแปญa tแบฅt cแบฃ cรกc ngรy trong tuแบงn แบก:\n- Sรกng: 6h00 - 11h00\n- Chiแปu: 13h00 - 22h00\nRiรชng cuแปi tuแบงn (thแปฉ 7, chแปง nhแบญt) mแป ฤแบฟn 23h00 tแปi."
      ]
    },
    {
      "tag": "location",
      "patterns": [
        "cแปญa hรng แป ฤรขu",
        "ฤแปa chแป cแปญa hรng",
        "chแป cรกc bแบกn แป ฤรขu",
        "cรณ chi nhรกnh nรo",
        "cรณ cฦก sแป nรo khรกc khรดng",
        "cแปญa hรng nแบฑm แป ฤรขu",
        "ฤแปa chแป chรญnh xรกc",
        "cรณ bแบฃn ฤแป khรดng",
        "chแป ฤฦฐแปng ฤi",
        "cรณ gแบงn ฤรขy khรดng",
        "cรณ แป quแบญn 1 khรดng",
        "cรณ แป hแป chรญ minh khรดng",
        "cรณ แป hร nแปi khรดng",
        "cรณ giao hรng quแบญn 7 khรดng"
      ],
      "responses": [
        "Cแปญa hรng chรญnh cแปงa chรบng tรดi tแปa lแบกc tแบกi: 123 ฤฦฐแปng Nguyแปn Vฤn Linh, Quแบญn 7, TP.HCM. Bแบกn cรณ thแป tรฌm thแบฅy chรบng tรดi trรชn Google Maps vแปi tแปซ khรณa 'Nhร hรng ABC'. Chรบng tรดi cลฉng cรณ dแปch vแปฅ giao hรng tแบญn nฦกi trong phแบกm vi 10km แบก.",
        "ฤแปa chแป cแปญa hรng: 123 ฤฦฐแปng Nguyแปn Vฤn Linh, Quแบญn 7, TP.HCM. Chรบng tรดi nแบฑm ngay gแบงn trung tรขm thฦฐฦกng mแบกi SC VivoCity. Hiแปn tแบกi chรบng tรดi mแปi chแป cรณ 1 cฦก sแป tแบกi ฤรขy แบก. Bแบกn cแบงn chแป ฤฦฐแปng khรดng แบก?",
        "Chรบng tรดi ฤแบทt tแบกi 123 ฤฦฐแปng Nguyแปn Vฤn Linh, Quแบญn 7, TP.HCM. Giแป mแป cแปญa tแปซ 6h sรกng ฤแบฟn 10h tแปi tแบฅt cแบฃ cรกc ngรy trong tuแบงn. Bแบกn cรณ thแป ghรฉ thฤm hoแบทc ฤแบทt hรng online ฤแป ฤฦฐแปฃc giao tแบญn nฦกi แบก."
      ]
    },
    {
      "tag": "promotion",
      "patterns": [
        "cรณ khuyแบฟn mรฃi gรฌ khรดng",
        "ฤang cรณ chฦฐฦกng trรฌnh gรฌ",
        "cรณ giแบฃm giรก khรดng",
        "cรณ mรฃ giแบฃm giรก khรดng",
        "cรณ ฦฐu ฤรฃi gรฌ khรดng",
        "cรณ khuyแบฟn mแบกi gรฌ hรดm nay",
        "cรณ combo nรo rแบป khรดng",
        "cรณ ฤแปng giรก khรดng",
        "cรณ mรณn nรo ฤang sale",
        "cรณ chฦฐฦกng trรฌnh khuyแบฟn mรฃi gรฌ",
        "cรณ ฦฐu ฤรฃi cho khรกch mแปi khรดng",
        "cรณ giแบฃm giรก cho ฤฦกn hรng lแปn khรดng"
      ],
      "responses": [
        "Hiแปn tแบกi chรบng tรดi ฤang cรณ cรกc chฦฐฦกng trรฌnh khuyแบฟn mรฃi hแบฅp dแบซn sau แบก:\n- Giแบฃm 20% cho ฤฦกn hรng tแปซ 200,000ฤ trแป lรชn (รกp dแปฅng mรฃ GIAM20)\n- Mua 1 tแบทng 1 cรกc mรณn nฦฐแปc mแปi thแปฉ 3 hรng tuแบงn\n- Miแปn phรญ ship cho ฤฦกn tแปซ 50,000ฤ trแป lรชn\n- Giแบฃm 10% cho khรกch hรng mแปi (รกp dแปฅng lแบงn ฤแบงu ฤแบทt hรng)\n\nBแบกn muแปn biแบฟt thรชm thรดng tin chi tiแบฟt vแป chฦฐฦกng trรฌnh nรo แบก?",
        "Chรบng tรดi luรดn cรณ nhiแปu ฦฐu ฤรฃi dรnh cho khรกch hรng แบก:\n\n๐ฅ COMBO ฦฏU ฤรI:\n- Combo 2 ngฦฐแปi: 1 phแป bรฒ + 1 bรกnh mรฌ + 2 nฦฐแปc: 80,000ฤ (tiแบฟt kiแปm 20,000ฤ)\n- Combo gia ฤรฌnh: 3 mรณn chรญnh + 3 nฦฐแปc: 150,000ฤ (tiแบฟt kiแปm 30,000ฤ)\n\n๐ KHUYแบพN MรI KHรC:\n- Tแบทng trร ฤรก miแปn phรญ cho mแปi ฤฦกn hรng\n- Giแบฃm 30% cho ฤฦกn hรng tแปซ 300,000ฤ (รกp dแปฅng mรฃ GIAM30)\n- Tรญch ฤiแปm ฤแปi quร cho khรกch hรng thรขn thiแบฟt\n\nBแบกn quan tรขm ฤแบฟn chฦฐฦกng trรฌnh nรo แบก?",
        "Hiแปn tแบกi chรบng tรดi ฤang cรณ cรกc chฦฐฦกng trรฌnh ฦฐu ฤรฃi sau แบก:\n\n1. Giแบฃm 10% cho ฤฦกn hรng tแปซ 100,000ฤ\n2. Miแปn phรญ ship cho ฤฦกn tแปซ 50,000ฤ\n3. Tแบทng nฦฐแปc ngแปt cho ฤฦกn hรng tแปซ 150,000ฤ\n4. Giแบฃm 20% cho khรกch hรng mแปi (รกp dแปฅng lแบงn ฤแบงu)\n5. Tแบทng voucher 50,000ฤ cho ฤฦกn hรng tiแบฟp theo\n\nBแบกn muแปn biแบฟt thรชm chi tiแบฟt vแป chฦฐฦกng trรฌnh nรo khรดng แบก?"
      ]
    },
    {
      "tag": "contact",
      "patterns": [
        "sแป ฤiแปn thoแบกi liรชn hแป",
        "gแปi ฤiแปn ฤแบทt hรng",
        "hotline lร gรฌ",
        "sแป ฤiแปn thoแบกi cแปญa hรng",
        "cรณ zalo khรดng",
        "cรณ facebook khรดng",
        "liรชn hแป thแบฟ nรo",
        "cรณ hแป trแปฃ online khรดng",
        "cรณ tฦฐ vแบฅn qua ฤiแปn thoแบกi khรดng",
        "sแป ฤiแปn thoแบกi ฤแบทt bรn",
        "gแบทp nhรขn viรชn tฦฐ vแบฅn"
      ],
      "responses": [
        "Bแบกn cรณ thแป liรชn hแป vแปi chรบng tรดi qua cรกc kรชnh sau แบก:\n- Hotline ฤแบทt hรng: 1900 1234 (7h-22h hรng ngรy)\n- Zalo: 0909 123 456\n- Facebook: facebook.com/nhahangABC\n- Email: info@nhahangabc.com\n- ฤแปa chแป: 123 ฤฦฐแปng Nguyแปn Vฤn Linh, Quแบญn 7, TP.HCM\n\nฤแปi ngลฉ nhรขn viรชn cแปงa chรบng tรดi luรดn sแบตn sรng hแป trแปฃ bแบกn tแปซ 6h sรกng ฤแบฟn 10h tแปi mแปi ngรy แบก.",
        "ฤแป ฤฦฐแปฃc tฦฐ vแบฅn vร ฤแบทt hรng, bแบกn cรณ thแป liรชn hแป:\n๐ Hotline: 1900 1234 (7h-22h)\n๐ฌ Zalo: 0909 123 456\n๐ Facebook: facebook.com/nhahangABC\n๐ ฤแปa chแป: 123 ฤฦฐแปng Nguyแปn Vฤn Linh, Quแบญn 7, TP.HCM\n\nChรบng tรดi luรดn sแบตn sรng phแปฅc vแปฅ bแบกn แบก!",
        "Thรดng tin liรชn hแป cแปงa chรบng tรดi แบก:\n\nโข ฤiแปn thoแบกi: 1900 1234 (7h-22h)\nโข Zalo: 0909 123 456\nโข Facebook: facebook.com/nhahangABC\nโข ฤแปa chแป: 123 ฤฦฐแปng Nguyแปn Vฤn Linh, Quแบญn 7, TP.HCM\nโข Giแป mแป cแปญa: 6h00 - 22h00 hรng ngรy\n\nBแบกn cแบงn hแป trแปฃ gรฌ แบก?"
      ]
    },
    {
      "tag": "food_quality",
      "patterns": [
        "ฤแป ฤn cรณ ngon khรดng",
        "cรณ ฤแบฃm bแบฃo vแป sinh khรดng",
        "nguแปn gแปc thแปฑc phแบฉm",
        "cรณ tฦฐฦกi sแปng khรดng",
        "cรณ ฤแบฃm bแบฃo an toรn thแปฑc phแบฉm khรดng",
        "cรณ mรณn chay khรดng",
        "cรณ mรณn ฤn kiรชng khรดng",
        "cรณ mรณn รญt dแบงu mแปก khรดng",
        "cรณ mรณn ฤn healthy khรดng",
        "cรณ mรณn cho ngฦฐแปi tiแปu ฤฦฐแปng khรดng",
        "cรณ mรณn cho trแบป em khรดng",
        "cรณ phแบงn ฤn nhแบน khรดng"
      ],
      "responses": [
        "Chรบng tรดi tแปฑ hรo vแป chแบฅt lฦฐแปฃng phแปฅc vแปฅ vร vแป sinh an toรn thแปฑc phแบฉm แบก. Tแบฅt cแบฃ nguyรชn liแปu ฤแปu ฤฦฐแปฃc chแปn lแปc kแปน lฦฐแปกng tแปซ cรกc nhร cung cแบฅp uy tรญn, cรณ nguแปn gแปc rรต rรng vร ฤแบฃm bแบฃo tฦฐฦกi ngon. ฤแบงu bแบฟp cแปงa chรบng tรดi ฤแปu lร nhแปฏng ngฦฐแปi cรณ tay nghแป cao vร ฤฦฐแปฃc ฤรo tแบกo bรi bแบฃn vแป vแป sinh an toรn thแปฑc phแบฉm.",
        "Vแป chแบฅt lฦฐแปฃng mรณn ฤn, chรบng tรดi cam kแบฟt:\n- Nguyรชn liแปu tฦฐฦกi ngon, cรณ nguแปn gแปc rรต rรng\n- Quy trรฌnh chแบฟ biแบฟn ฤแบฃm bแบฃo vแป sinh\n- Khรดng sแปญ dแปฅng phแปฅ gia ฤแปc hแบกi\n- Thแปฑc ฤฦกn ฤa dแบกng, phรน hแปฃp nhiแปu ฤแปi tฦฐแปฃng\n\nChรบng tรดi cลฉng cรณ nhiแปu lแปฑa chแปn cho thแปฑc khรกch ฤn kiรชng, ฤn chay vร trแบป em แบก.",
        "Chแบฅt lฦฐแปฃng vร vแป sinh an toรn thแปฑc phแบฉm lร ฦฐu tiรชn hรng ฤแบงu cแปงa chรบng tรดi แบก. Chรบng tรดi cรณ:\nโข Nguแปn cung cแบฅp thแปฑc phแบฉm uy tรญn, cรณ giแบฅy tแป ฤแบงy ฤแปง\nโข Quy trรฌnh chแบฟ biแบฟn khรฉp kรญn, ฤแบฃm bแบฃo vแป sinh\nโข ฤแบงu bแบฟp chuyรชn nghiแปp, cรณ chแปฉng chแป an toรn thแปฑc phแบฉm\nโข Thแปฑc ฤฦกn ฤa dแบกng, phรน hแปฃp nhiแปu nhu cแบงu: mรณn chay, mรณn kiรชng, mรณn healthy...\n\nBแบกn cรณ yรชu cแบงu ฤแบทc biแปt gรฌ vแป mรณn ฤn khรดng แบก?"
      ]
    }
  ]
}
